setup.py
distributionsppk/Binomialdistribution.py
distributionsppk/Gaussiandistribution.py
distributionsppk/Generaldistribution.py
distributionsppk/__init__.py
distributionsppk.egg-info/PKG-INFO
distributionsppk.egg-info/SOURCES.txt
distributionsppk.egg-info/dependency_links.txt
distributionsppk.egg-info/not-zip-safe
distributionsppk.egg-info/top_level.txt