Metadata-Version: 1.0
Name: distributionsppk
Version: 0.1
Summary: Gaussian distributions
Home-page: UNKNOWN
Author: Pyae Phyo Kyaw
Author-email: pyaekyaw1571999@gmail.com
License: UNKNOWN
Platform: UNKNOWN
